{
	"id": 1,
	"jsonrpc": "2.0",
	"total": 6,
	"result": [
		{
			"id": 1,
			"guid": "1d4aa3b2-c059-4fa7-a751-9bca735e4ea1",
			"thumb": "http://skounis.s3.amazonaws.com/mobile-apps/restaurant-ionic/_greekdemonstration/assets/cat-a-1-thumb.jpg",
			"title": "Σουβλάκι Χοιρινό",
			"body": "συνοδεόνται από σαλάτα εποχής και πατατοσαλάτα χειροποίητο.",
			"tags": ["χοιρινό", "σουβλάκι"],
			"standardOptions":[
				{
					"name": "Σαλάτα εποχής",
					"selected": true
				},
				{
					"name": "Πατατοσαλάτα χειροποίητο",
					"selected": true
				}
			],
			"extraOptions": [],
			"price" : [
				{
					"name": "1 τεμ.",
					"value": "$1.70"
				},
				{
					"name": "2 τεμ.",
					"value": "$3.30"
				},
				{
					"name": "3 τεμ.",
					"value": "$4.90"
				}
			],
			"pictures": [
				"http://skounis.s3.amazonaws.com/mobile-apps/restaurant-ionic/_greekdemonstration/assets/cat-a-1-1.jpg"
			]
		}, {
			"id": 2,
			"guid": "1d4aa3b2-c059-4fa7-a751-9bca735e4eb1",
			"thumb": "http://skounis.s3.amazonaws.com/mobile-apps/restaurant-ionic/_greekdemonstration/assets/cat-b-1-thumb.jpg",
			"title": "Ρόκα",
			"body": "Συνδυάστε ρόκα και μαρούλι με γλυκά ντοματίνια, παραδοσιακό κεφαλοτύρι, καρύδια, ελαιόλαδο, και εκλεκτό ξύδι από κόκκινα σταφύλια.",
			"tags": ["ρόκα", "μαρούλι"],
			"standardOptions":[
				{
					"name": "Ρόκα",
					"selected": true
				},
				{
					"name": "Μαρούλι",
					"selected": true
				},
				{
					"name": "Τοματίνια",
					"selected": true
				},
				{
					"name": "Κεφαλοτύρι",
					"selected": true
				},
				{
					"name": "Καρύδια",
					"selected": true
				}
			],
			"extraOptions": [],
			"price" : [
			{
				"name": "Κανονικό",
				"value": "$3.00"
			}
			],
			"pictures": [
				"http://skounis.s3.amazonaws.com/mobile-apps/restaurant-ionic/_greekdemonstration/assets/cat-b-1-1.jpg"
			]
		}, {
			"id": 3,
			"guid": "1d4aa3b2-c059-4fa7-a751-9bca735e4ebc1",
			"thumb": "http://skounis.s3.amazonaws.com/mobile-apps/restaurant-ionic/_greekdemonstration/assets/cat-c-1-thumb.jpg",
			"title": "Σουβλάκι Χοιρινό",
			"body": "από διαλεχτό κομμάτι.",
			"tags": ["σουβλάκι", "χοιρινό"],
			"standardOptions":[],
			"extraOptions": [],
			"price" : [
			{
				"name": "Τεμ.",
				"value": "$1.20"
			}
			],
			"pictures": [
				"http://skounis.s3.amazonaws.com/mobile-apps/restaurant-ionic/_greekdemonstration/assets/cat-c-1-1.jpg"
			]
		}, {
			"id": 4,
			"guid": "1d4aa3b2-c059-4fa7-a751-9bca735e4ed1",
			"thumb": "http://skounis.s3.amazonaws.com/mobile-apps/restaurant-ionic/_greekdemonstration/assets/cat-d-1-thumb.jpg",
			"title": "Πατάτα",
			"body": "φρεσκοτηγανισμένη.",
			"tags": ["πατάτα", "τηγανητή"],
			"standardOptions":[],
			"extraOptions": [],
			"price" : [
			{
				"name": "Κανονικό",
				"value": "$1.80"
			}
			],
			"pictures": [
				"http://skounis.s3.amazonaws.com/mobile-apps/restaurant-ionic/_greekdemonstration/assets/cat-d-1-1.jpg"
			]
		}, {
			"id": 5,
			"guid": "1y4aa3b2-c059-4fa7-a751-9bca735e4ee1",
			"thumb": "http://skounis.s3.amazonaws.com/mobile-apps/restaurant-ionic/_greekdemonstration/assets/cat-e-1-thumb.jpg",
			"title": "Κλασικό Μεγάλο με Σουβλάκι Χοιρινό",
			"body": "σε πίτα ή λαγάνα, με πατάτα, ντομάτα, κέτσαπ, μουστάρδα, κρεμμύδι και 2 τεμ. σουβλάκι χοιρινό.",
			"tags": ["σάντουιτς", "σουβλάκι χοιρινό"],
			"standardOptions":[
				{
					"name": "Πατάτα",
					"selected": true
				},
				{
					"name": "Ντομάτα",
					"selected": true
				},
				{
					"name": "Κέτσαπ",
					"selected": true
				},
				{
					"name": "Μουστάρδα",
					"selected": true
				},
				{
					"name": "Κρεμμύδι",
					"selected": true
				}
			],
			"extraOptions": [
				{
					"name": "Τζατζίκι",
					"selected": false,
					"value": "0.20"
				},
				{
					"name": "Τυροσαλάτα",
					"selected": false,
					"value": "0.20"
				},
				{
					"name": "Μελιτζανοσαλάτα",
					"selected": false,
					"value": "0.20"
				}
			],
			"price" : [
			{
				"name": "Πίτα",
				"value": "$2.90"
			},
			{
				"name": "Λαγάνα",
				"value": "$2.90"
			}
			],
			"pictures": [
				"http://skounis.s3.amazonaws.com/mobile-apps/restaurant-ionic/_greekdemonstration/assets/cat-e-1-1.jpg"
			]
		}, {
			"id": 6,
			"guid": "1d4ab452-c0k9-4fa0-a731f-9bca735e4ebc1",
			"thumb": "http://skounis.s3.amazonaws.com/mobile-apps/restaurant-ionic/_greekdemonstration/assets/cat-f-1-thumb.jpg",
			"title": "Τζατζίκι",
			"body": "παραδοσιακό ταιριαστό με όλες τις γεύσεις.",
			"tags": ["τζατζίκι"],
			"standardOptions":[],
			"extraOptions": [],
			"price" : [
			{
				"name": "Κανονικό",
				"value": "$2.40"
			}
			],
			"pictures": [
				"http://skounis.s3.amazonaws.com/mobile-apps/restaurant-ionic/_greekdemonstration/assets/cat-f-1-1.jpg"
			]
		}
	]
}
